snspec/__init__.py
snspec/snspec.py
snspec-0.0.11.dist-info/LICENSE
snspec-0.0.11.dist-info/METADATA
snspec-0.0.11.dist-info/WHEEL
snspec-0.0.11.dist-info/top_level.txt
snspec-0.0.11.dist-info/RECORD
